django_old_records/__init__.py
django_old_records/admin.py
django_old_records/apps.py
django_old_records/models.py
django_old_records/old_records_manager.py
django_old_records/queryset_csv_exporter.py
django_old_records/tests.py
django_old_records/views.py
django_old_records/management/commands/purge_old_records.py
django_old_records/migrations/0001_initial.py
django_old_records/migrations/__init__.py
django_old_records-2.0.8.dist-info/LICENSE
django_old_records-2.0.8.dist-info/METADATA
django_old_records-2.0.8.dist-info/WHEEL
django_old_records-2.0.8.dist-info/top_level.txt
django_old_records-2.0.8.dist-info/RECORD
